CHANGES.txt
CONTRIBUTORS.txt
MANIFEST.in
README.txt
setup.py
docs/HISTORY.txt
docs/INSTALL.txt
docs/LICENSE.GPL
docs/LICENSE.txt
mailtoplone/__init__.py
mailtoplone.base.egg-info/PKG-INFO
mailtoplone.base.egg-info/SOURCES.txt
mailtoplone.base.egg-info/dependency_links.txt
mailtoplone.base.egg-info/entry_points.txt
mailtoplone.base.egg-info/namespace_packages.txt
mailtoplone.base.egg-info/not-zip-safe
mailtoplone.base.egg-info/requires.txt
mailtoplone.base.egg-info/top_level.txt
mailtoplone/base/CHANGELOG
mailtoplone/base/README.rst
mailtoplone/base/TODO.rst
mailtoplone/base/__init__.py
mailtoplone/base/adapter.py
mailtoplone/base/config.py
mailtoplone/base/configure.zcml
mailtoplone/base/events.py
mailtoplone/base/interfaces.py
mailtoplone/base/myutils.py
mailtoplone/base/utilities.py
mailtoplone/base/version.txt
mailtoplone/base/adapters/__init__.py
mailtoplone/base/adapters/blog.py
mailtoplone/base/adapters/configure.zcml
mailtoplone/base/adapters/event.py
mailtoplone/base/browser/__init__.py
mailtoplone/base/browser/configure.zcml
mailtoplone/base/browser/emailview.pt
mailtoplone/base/browser/emailview.py
mailtoplone/base/browser/xmlrpcview.py
mailtoplone/base/browser/images/Email_icon.gif
mailtoplone/base/browser/images/InBox_icon.gif
mailtoplone/base/content/__init__.py
mailtoplone/base/content/configure.zcml
mailtoplone/base/content/email.py
mailtoplone/base/content/inbox.py
mailtoplone/base/doc/BLOG.rst
mailtoplone/base/doc/EVENT.rst
mailtoplone/base/doc/calendars.eml
mailtoplone/base/portlets/__init__.py
mailtoplone/base/portlets/configure.zcml
mailtoplone/base/profiles/default/factorytool.xml
mailtoplone/base/profiles/default/metadata.xml
mailtoplone/base/profiles/default/propertiestool.xml
mailtoplone/base/profiles/default/rolemap.xml
mailtoplone/base/profiles/default/types.xml
mailtoplone/base/profiles/default/types/Email.xml
mailtoplone/base/profiles/default/types/InBox.xml
mailtoplone/base/scripts/dropemail
mailtoplone/base/tests/__init__.py
mailtoplone/base/tests/base.py
mailtoplone/base/tests/test_bodyfactory.py
mailtoplone/base/tests/test_doctests.py
mailtoplone/base/tests/test_emailview.py
mailtoplone/base/tests/test_eventfactory.py
mailtoplone/base/tests/test_eventfactory_examples.py
mailtoplone/base/tests/test_setup.py
mailtoplone/base/tests/data/apple.ics
