Metadata-Version: 1.0
Name: mailtoplone.base
Version: 0.2.7
Summary: basic package for mailtoplone
Home-page: https://svn.plone.org/svn/collective/mailtoplone/mailtoplone.base
Author: Hans-Peter Locher
Author-email: hans-peter.locher@inquant.de
License: GPL
Platform: UNKNOWN
Classifier: Framework :: Plone
Classifier: Framework :: Zope2
Classifier: Framework :: Zope3
Classifier: Programming Language :: Python
Classifier: Topic :: Software Development :: Libraries :: Python Modules
